setup.py
openross/__init__.py
openross/engine.py
openross/errors.py
openross/image_modes.py
openross/middleware.py
openross/settings.py
openross/test_settings.py
openross/utils.py
openross.egg-info/PKG-INFO
openross.egg-info/SOURCES.txt
openross.egg-info/dependency_links.txt
openross.egg-info/not-zip-safe
openross.egg-info/requires.txt
openross.egg-info/top_level.txt
openross/endpoint/__init__.py
openross/endpoint/factory.py
openross/endpoint/healthcheck.py
openross/pipeline/__init__.py
openross/pipeline/cache_check.py
openross/pipeline/cacher.py
openross/pipeline/resizer.py
openross/pipeline/s3_downloader.py
openross/twisted/plugins/bobross_plugin.py