Metadata-Version: 1.1
Name: openross
Version: 0.1.0
Summary: Open BobRoss Image Processor
Home-page: http://www.lyst.com
Author: LYST Ltd
Author-email: data@ly.st
License: Apache 2.0 Licence
Platform: UNKNOWN
Classifier: Development Status :: 5 - Production/Stable
Classifier: License :: OSI Approved :: Apache Software License
Classifier: Programming Language :: Python :: 2.7
Classifier: Topic :: Multimedia :: Graphics
